prefect_kv/__init__.py
prefect_kv/_backend.py
prefect_kv/_version.py
prefect_kv-0.1.0.dist-info/LICENSE
prefect_kv-0.1.0.dist-info/METADATA
prefect_kv-0.1.0.dist-info/WHEEL
prefect_kv-0.1.0.dist-info/entry_points.txt
prefect_kv-0.1.0.dist-info/top_level.txt
prefect_kv-0.1.0.dist-info/RECORD
